<?xml version="1.0" encoding="utf-8"?>
<publishData>
  <publishProfile publishUrl="D:\Abhishek\MCADump\CustomerServiceHost" deleteExistingFiles="True" ftpAnonymousLogin="False" ftpPassiveMode="True" msdeploySite="" msdeploySiteID="" msdeployRemoteSitePhysicalPath="" msdeployAllowUntrustedCertificate="False" msdeploySkipExtraFilesOnServer="True" msdeployMarkAsApp="False" profileName="Profile1" publishMethod="FileSystem" replaceMatchingFiles="False" userName="" savePWD="False" userPWD="" SelectedForPublish="True">
    <file relUrl="bin/CustomerService.pdb" publishTime="10/27/2015 09:57:07" />
    <file relUrl="bin/ServiceUtility.dll" publishTime="10/22/2015 11:44:06" />
    <file relUrl="DataSource/GetCustomerVerificationDetails/904289.xml" publishTime="10/20/2015 14:48:09" />
    <file relUrl="bin/ServiceUtility.pdb" publishTime="10/22/2015 11:44:06" />
    <file relUrl="bin/CustomerService.dll" publishTime="10/27/2015 09:57:07" />
    <file relUrl="Web.config" publishTime="10/22/2015 12:16:47" />
    <file relUrl="DataSource/GetCustomerDetails/en-GB/634004022010553358.xml" publishTime="10/20/2015 14:23:16" />
    <file relUrl="DataSource/GetCustomerDetails/en-GB/904289.xml" publishTime="10/20/2015 12:36:54" />
    <file relUrl="CustomerService.svc" publishTime="10/12/2015 10:48:13" />
    <file relUrl="DataSource/GetConfigDetails/en-GB/Config.xml" publishTime="10/26/2015 16:03:25" />
    <file relUrl="DataSource/GetCustomerDetails/en-GB/634004024007890751.xml" publishTime="10/20/2015 15:07:25" />
    <file relUrl="DataSource/SearchCustomer/en-GB/904289.xml" publishTime="10/20/2015 14:50:28" />
    <file relUrl="DataSource/GetCustomerDetails/en-GB/0.xml" publishTime="10/20/2015 14:27:46" />
  </publishProfile>
</publishData>