<?xml version="1.0" encoding="utf-8"?>
<ManageCards-App_LocalResources>
  <ViewMyCards.cshtml.en-GB.resx>
    <Data key="AndSeprator" value="and" />
    <Data key="CardnumberResource1" value="Clubcard number" />
    <Data key="CardsVariousResource1" value="All the cards saved to your account." />
    <Data key="CardsVariousResource1" value="Since joining Clubcard you may have collected various Clubcards. Below are the card numbers that we hold in this account." />
    <Data key="CommunicateMsg1Resource1" value=" Free from BT landlines. Other providers may vary. Calls may be recorded." />
    <Data key="CommunicateMsg2Resource1" value=" Charged at the local rate from mobiles and private phones." />
    <Data key="CustomerTypeAssoc" value="Associate cardholder" />
    <Data key="CustomerTypeMain" value="Main cardholder" />
    <Data key="FAQSResource1" value="" />
    <Data key="furtheirdtlsResource1" value="" />
    <Data key="LasttimeusedResource1" value="Date last used" />
    <Data key="lclAnothercardlistedResource1" value="If you want to add another card to this account or want to leave Clubcard, call us on " />
    <Data key="lclAnothercardlistedResource2" value="&lt;br/&gt;&lt;br/&gt;You can also add one other person from your household to your account. Please make sure the person you want to add is with you when you call." />
    <Data key="lclMore" value="More than 6 months" />
    <Data key="lclNameAccResource1" value="Name(s) on account:" />
    <Data key="lcltollfree1Resource1" value="0800 591 688&lt;sup&gt;1&lt;/sup&gt;" />
    <Data key="lcltollfree1starResource1" value="" />
    <Data key="lcltollfree2Resource2" value="or 0330 123 1688&lt;sup&gt;2&lt;/sup&gt;." />
    <Data key="lcltollfree2starResource2" value="" />
    <Data key="lclVwCradsResource1" value="Clubcards on account" />
    <Data key="Literal1Resource1" value="" />
    <Data key="Localize1Resource1" value="" />
    <Data key="Localize4Resource1" value="0800 591 688" />
    <Data key="Localize5Resource1" value="If you have another card not listed here or would like to leave the scheme, please contact us on 0800 591 688. You can also add one other person from your household to your account, the other person will need to be present when you call." />
    <Data key="Localize6Resource1" value="" />
    <Data key="ltrCardHeaderResource1" value="" />
    <Data key="ltrNamesResource1" value="Names on account" />
    <Data key="PageResource1Title" value="Cards" />
    <Data key="Typeofcard" value="Type of card" />
    <Data key="WhereResource1" value="Transaction details" />
    <Data key="CardHolder" value=" card holder -" />
    <Data key="tdAsscardholder" value="Other cardholder" />
    <Data key="tdMainCardholder" value="Main cardholder" />
    <Data key="thcardholdername" value="Cardholder name" />
  </ViewMyCards.cshtml.en-GB.resx>
</ManageCards-App_LocalResources>